message_notify_python
